edf_neon_server/__init__.py
edf_neon_server/__version__.py
edf_neon_server/config.py
edf_neon_server/main.py
edf_neon_server/storage.py
edf_neon_server/synchronizer.py
edf_neon_server/analyzer/__init__.py
edf_neon_server/analyzer/helper.py
edf_neon_server/analyzer/task.py
edf_neon_server/api/__init__.py
edf_neon_server/api/case.py
edf_neon_server/api/config.py
edf_neon_server/api/search.py
edf_neon_server/helper/__init__.py
edf_neon_server/helper/aiohttp.py
edf_neon_server-2.0.0.dist-info/licenses/LICENSE
edf_neon_server-2.0.0.dist-info/METADATA
edf_neon_server-2.0.0.dist-info/WHEEL
edf_neon_server-2.0.0.dist-info/entry_points.txt
edf_neon_server-2.0.0.dist-info/top_level.txt
edf_neon_server-2.0.0.dist-info/RECORD
